snuffled/__init__.py
snuffled/_core/__init__.py
snuffled/_core/analysis/__init__.py
snuffled/_core/analysis/_function_sampler.py
snuffled/_core/analysis/_property_extractor.py
snuffled/_core/analysis/snuffler.py
snuffled/_core/analysis/diagnostic/__init__.py
snuffled/_core/analysis/diagnostic/diagnostic_analyser.py
snuffled/_core/analysis/function/__init__.py
snuffled/_core/analysis/function/function_analyser.py
snuffled/_core/analysis/function/helpers_discontinuous.py
snuffled/_core/analysis/function/helpers_non_monotonic.py
snuffled/_core/analysis/roots/__init__.py
snuffled/_core/analysis/roots/roots_analyser.py
snuffled/_core/analysis/roots/single_root_one_side_analyser.py
snuffled/_core/analysis/roots/single_root_two_side_analyser.py
snuffled/_core/analysis/roots/curve_fitting/__init__.py
snuffled/_core/analysis/roots/curve_fitting/brute_force/__init__.py
snuffled/_core/analysis/roots/curve_fitting/brute_force/_fit_optimal_with_uncertainty.py
snuffled/_core/analysis/roots/curve_fitting/shared/__init__.py
snuffled/_core/analysis/roots/curve_fitting/shared/_curves_and_costs.py
snuffled/_core/analysis/roots/curve_fitting/shared/_function_sampling.py
snuffled/_core/analysis/roots/curve_fitting/specialized/__init__.py
snuffled/_core/analysis/roots/curve_fitting/specialized/_explore_uncertainty.py
snuffled/_core/analysis/roots/curve_fitting/specialized/_fit_exact.py
snuffled/_core/analysis/roots/curve_fitting/specialized/_fit_optimal.py
snuffled/_core/analysis/roots/curve_fitting/specialized/_fit_optimal_with_uncertainty.py
snuffled/_core/analysis/roots/curve_fitting/specialized/_helpers.py
snuffled/_core/compatibility/__init__.py
snuffled/_core/compatibility/_numba.py
snuffled/_core/compatibility/_strenum.py
snuffled/_core/models/__init__.py
snuffled/_core/models/base/__init__.py
snuffled/_core/models/base/_named_array.py
snuffled/_core/models/properties/__init__.py
snuffled/_core/models/properties/_all.py
snuffled/_core/models/properties/_diagnostic.py
snuffled-0.1.4.dist-info/METADATA
snuffled-0.1.4.dist-info/WHEEL
snuffled-0.1.4.dist-info/licenses/LICENSE
snuffled-0.1.4.dist-info/RECORD
