Metadata-Version: 2.4
Name: snuffled
Version: 0.1.4
Summary: Systematic Numerical Univariate Full-Function anaLysis for Establishing Difficulty of root-finding
Project-URL: Source, https://github.com/bertpl/snuffled
Project-URL: ChangeLog, https://github.com/bertpl/snuffled/blob/main/CHANGELOG.md
Project-URL: Issues, https://github.com/bertpl/snuffled/issues
Project-URL: Roadmap, https://github.com/bertpl/snuffled/milestones
Author-email: Bert Pluymers <bert.pluymers@gmail.com>
License-File: LICENSE
Requires-Python: >=3.10
Requires-Dist: backports-strenum>=1.3.1
Requires-Dist: numpy>=1.20
Provides-Extra: numba
Requires-Dist: numba>=0.50; extra == 'numba'
